LICENSE
MANIFEST.in
Makefile
README.md
README.rst
setup.py
crowdflower/__init__.py
crowdflower/cache.py
crowdflower/connection.py
crowdflower/exception.py
crowdflower/job.py
crowdflower/unit.py
crowdflower.egg-info/PKG-INFO
crowdflower.egg-info/SOURCES.txt
crowdflower.egg-info/dependency_links.txt
crowdflower.egg-info/requires.txt
crowdflower.egg-info/top_level.txt