Metadata-Version: 1.1
Name: crowdflower
Version: 0.0.9
Summary: CrowdFlower API - Python client
Home-page: https://github.com/chbrown/crowdflower
Author: Christopher Brown
Author-email: io@henrian.com
License: Copyright (c) 2014 Christopher Brown
